{
    "licData": {
        "licName": "011953",
        "licId": "08011953",
        "chName": "第凡內持久染髮霜8.64淺紅棕色",
        "enName": "EVA DIVINA GENERICS COLOURS 8.64 COPPERY REDDISH LIGHT BLONDE",
        "packDt": "500G以下 管裝,附外 紙盒裝",
        "doesId": "",
        "does": "霜劑",
        "drugMcId": "0110",
        "drugMcMa": "染髮劑",
        "purpose": "染頭髮。",
        "signId": "DHA00801195305",
        "efDate": "2014-02-22 00:00:00",
        "giDate": "2005-02-22 00:00:00",
        "gtLicDate": "2005-02-22 00:00:00",
        "exDate": "2009-12-03 00:00:00",
        "recvId": "",
        "canMark": "註銷",
        "lockMemo": "已解鎖",
        "restrMa": "02 輸　入 "
    },
    "expNmeData": [],
    "factData": {
        "factId": "CES0022000",
        "factName": "EVA ESPANOLA, S.L.",
        "factAddr": "RAMON FARGUELL 60, POL. IND. BUFALVENT, 08240 MANRESA (BARCELONA), SPAIN",
        "cid": "西班牙"
    },
    "presData": {
        "cresWrap": {
            "1": {
                "presId": 1,
                "oriPresName": "",
                "presName": "1",
                "titleNames": [
                    "含量"
                ],
                "datas": {
                    "1": {
                        "ingrName": "AMMONIA WATER (AMMONIUM HYDROXIDE)",
                        "unitMa": "%(W\/W)",
                        "oriPresName": "1",
                        "presId": 1,
                        "ingrDt": 9.4,
                        "ingrDtCol1": 9.4,
                        "ingrDtCol2": 0,
                        "ingrDtCol3": 0,
                        "rid": 1,
                        "rdtMemo": "(20%)"
                    },
                    "2": {
                        "ingrName": "2-NITRO-P-PHENYLENEDIAMINE",
                        "unitMa": "%(W\/W)",
                        "oriPresName": "1",
                        "presId": 1,
                        "ingrDt": 0.5621,
                        "ingrDtCol1": 0.5621,
                        "ingrDtCol2": 0,
                        "ingrDtCol3": 0,
                        "rid": 2,
                        "rdtMemo": null
                    },
                    "3": {
                        "ingrName": "P-PHENYLENEDIAMINE",
                        "unitMa": "%(W\/W)",
                        "oriPresName": "1",
                        "presId": 1,
                        "ingrDt": 0.1257,
                        "ingrDtCol1": 0.1257,
                        "ingrDtCol2": 0,
                        "ingrDtCol3": 0,
                        "rid": 3,
                        "rdtMemo": null
                    },
                    "4": {
                        "ingrName": "6-CHLORO-4-NITRO-2-AMINOPHENOL",
                        "unitMa": "%(W\/W)",
                        "oriPresName": "1",
                        "presId": 1,
                        "ingrDt": 0.1,
                        "ingrDtCol1": 0.1,
                        "ingrDtCol2": 0,
                        "ingrDtCol3": 0,
                        "rid": 4,
                        "rdtMemo": null
                    },
                    "5": {
                        "ingrName": "4-AMINO-2-HYDROXYTOLUENE",
                        "unitMa": "%(W\/W)",
                        "oriPresName": "1",
                        "presId": 1,
                        "ingrDt": 0.0831,
                        "ingrDtCol1": 0.0831,
                        "ingrDtCol2": 0,
                        "ingrDtCol3": 0,
                        "rid": 5,
                        "rdtMemo": null
                    }
                }
            }
        }
    },
    "authorData": {
        "cauthorListDto": []
    },
    "uploadData": {
        "cuploadFileListDto": [
            {
                "fileName": "080119530002.pdf",
                "tempFlag": "1",
                "fsk": "BB566149-E47E-4C09-BD1D-B6BEAFB65563"
            },
            {
                "fileName": "080119530001.pdf",
                "tempFlag": "1",
                "fsk": "0534965C-86E4-40FB-AA6A-DCDF4E1937A0"
            }
        ]
    },
    "modData": {
        "chModListDto": []
    },
    "changeData": null,
    "appData": {
        "appId": "",
        "appName": "得法國際美髮用品股份有限公司",
        "appAddr": "新北市中和區連城路268號11樓之1"
    }
}