{
    "licData": {
        "licName": "006927",
        "licId": "57006927",
        "chName": "1.亮采保濕抗UV隔離霜SPF50★★★、2.淨白保濕防曬乳SPF50★★★、3.清透煥白保濕BB霜SPF50★★★、4.保濕亮白防曬CC霜SPF50★★★",
        "enName": " 1. Whitening  Hydra-Multi Sunscreen Cream SPF 50★★★ 2. Whitening  Hydra-Multi Sunscreen Cream SPF 50★★★ 3. Whitening  Hydra-Multi Blemish Balm Cream SPF 50★★★ 4. Whitening  Hydra-Multi Sunscreen CC Cream SPF 50★★★",
        "packDt": "500gm以下 管裝附外盒",
        "doesId": "",
        "does": "乳霜劑",
        "drugMcId": "0714",
        "drugMcMa": "防晒化粧用品",
        "purpose": "防曬、美白保濕滋潤肌膚",
        "signId": "DHY05700692702",
        "efDate": "2024-06-30 00:00:00",
        "giDate": "2014-12-22 00:00:00",
        "gtLicDate": "2015-02-13 00:00:00",
        "exDate": "2019-11-01 00:00:00",
        "recvId": "",
        "canMark": "正常",
        "lockMemo": "已解鎖",
        "restrMa": "01 國　產"
    },
    "expNmeData": [],
    "factData": {
        "factId": "5821011086",
        "factName": "天仁生化工業股份有限公司",
        "factAddr": "台南市東區裕農路288巷110弄6號",
        "cid": "中華民國"
    },
    "presData": {
        "cresWrap": {
            "1": {
                "presId": 1,
                "oriPresName": "",
                "presName": "1",
                "titleNames": [
                    "含量"
                ],
                "datas": {
                    "1": {
                        "ingrName": "ETHYLHEXYL METHOXYCINNAMATE",
                        "unitMa": "%(W\/V)",
                        "oriPresName": "1",
                        "presId": 1,
                        "ingrDt": 8,
                        "ingrDtCol1": 8,
                        "ingrDtCol2": 0,
                        "ingrDtCol3": 0,
                        "rid": 1,
                        "rdtMemo": ""
                    },
                    "2": {
                        "ingrName": "BENZOPHENONE-3",
                        "unitMa": "%(W\/V)",
                        "oriPresName": "1",
                        "presId": 1,
                        "ingrDt": 2.5,
                        "ingrDtCol1": 2.5,
                        "ingrDtCol2": 0,
                        "ingrDtCol3": 0,
                        "rid": 2,
                        "rdtMemo": ""
                    },
                    "3": {
                        "ingrName": "AVOBENZONE",
                        "unitMa": "%(W\/V)",
                        "oriPresName": "1",
                        "presId": 1,
                        "ingrDt": 1,
                        "ingrDtCol1": 1,
                        "ingrDtCol2": 0,
                        "ingrDtCol3": 0,
                        "rid": 3,
                        "rdtMemo": ""
                    },
                    "4": {
                        "ingrName": "OCTOCRYLENE",
                        "unitMa": "%(W\/V)",
                        "oriPresName": "1",
                        "presId": 1,
                        "ingrDt": 6,
                        "ingrDtCol1": 6,
                        "ingrDtCol2": 0,
                        "ingrDtCol3": 0,
                        "rid": 4,
                        "rdtMemo": ""
                    }
                }
            }
        }
    },
    "authorData": {
        "cauthorListDto": []
    },
    "uploadData": {
        "cuploadFileListDto": [
            {
                "fileName": "57006927-104-03-20.pdf",
                "tempFlag": "1",
                "fsk": "B2B9A980-D7AA-4208-ADA4-411ED393A275"
            }
        ]
    },
    "modData": {
        "chModListDto": []
    },
    "changeData": null,
    "appData": {
        "appId": "",
        "appName": "天仁生化工業股份有限公司",
        "appAddr": "台南市東區裕農路288巷110弄6號"
    }
}