{
    "cancelStatus": "1",
    "cancelDate": "2014-02-27",
    "cancelReason": [
        "841"
    ],
    "licid": "42000499",
    "validDate": "2018-03-01 00:00:00.000",
    "issueDate": "2013-03-01 00:00:00.000",
    "licKind": "09",
    "oldLicid": null,
    "certNo": "DHA04200049902",
    "prodNameC": "百略威爾舒電子血壓計",
    "prodNameE": "Microlife WatchBP Digital Blood Pressure Monitor",
    "indicationsName": [],
    "does": null,
    "packageUnit": [],
    "medMCode": null,
    "maMedCode": null,
    "medDCode": null,
    "ingredientsDesc": [],
    "restraintItemsCode": [
        "R02",
        "R03"
    ],
    "applicantName": "百略醫學科技股份有限公司",
    "applicantAddr": "台北市內湖區瑞光路431號9樓",
    "medClass": "2",
    "efficacy": "詳如中文仿單核定本 ",
    "mdFormat": "BP3MX1-1以下空白",
    "productAnnotation": null,
    "mdKind": [
        {
            "mdKindMCode": "E",
            "mdKindMCodeName": "E 心臟血管用裝置",
            "mdKindDCode": "E.1130",
            "mdKindDCodeName": "E.1130 非侵入性血壓測量系統",
            "checkChange": "Y"
        }
    ],
    "monitorDate": null,
    "licidNew": null,
    "licidOld": null,
    "factoryDtoList": [
        {
            "factoryCode": "1",
            "factoryName": "ONBO ELECTRONIC (SHENZHEN) CO., LTD",
            "factoryAddr": "NO.497 TALANEG NAN ROAD INDUSTRIAL ZONE, LOONG HWA CHEN BAOAN SHIN SHENZHEN CHINA",
            "factoryCompanyAddr": null,
            "countryCode": "CN",
            "processCode": [],
            "processCodeStr": null,
            "factoryKind": "M",
            "factoryNo": "MCN0929000",
            "factoryInfo": "1",
            "qsd": null
        }
    ],
    "ingredientsDtoList": [],
    "authDtoList": [],
    "iomDtoList": [
        {
            "fileType": "2",
            "fileName": "420004990001___20130401.pdf",
            "fileStreamId": "449B4351-56AA-4B0A-845C-D82DC53D08CF"
        },
        {
            "fileType": "1",
            "fileName": "420004990001___20130401.pdf",
            "fileStreamId": "58D108BC-358A-4CF4-8764-B63CBDB7384E"
        }
    ],
    "changeDtoList": [],
    "atcList": [],
    "licBaseId": "746984A5-9AA2-492A-B6FB-E260193E204D"
}